{
  "name": "Arithmetic",
  "order": 1,
  "challenges": [
    {
      "title": "Write your first Fraction",
      "description": [
        "To write your first vertical fraction using LaTeX, you'll need to add <code>\\frac{1}{2}</code>, where 1 and 2 can be any valid expression or number.",
        "Notice that if you don't use this special syntax (for example <code>3/4</code>), the fraction will be rendered horizontally. If you did it correctly the fraction will be rendered vertically",
        "In LaTeX, is necessary to enclose every math expressions between <code>\\[ \\]</code>  or <code>$$ $$</code> "
      ],
      "challengeSeed": [
        "% Write your LaTeX expression inside the delimiters",
        "\\[  \\]",
        ""
      ],
      "tests": [
        "assert(/(\\\\\\[.*\\\\\\]|\\$\\$.*\\$\\$)/g.test(expression), 'message: The expression should be enclosed by Math LaTeX equation delimiters <code>\\[ \\]</code> or <code>$$ $$</code>')",
        "assert(/\\\\frac(\\s*{.*}\\s*{.*}|\\s*(\\d|\\w)\\s*(\\d|\\w))/g.test(expression), 'message: The expression should have a valid fraction.')"
      ],
      "solutions": [
        "\\[ \\frac{1}{2} \\]"
      ]
    },
    {
      "title": "Compare Fractions that have Common Denominators",
      "description": [
        "When comparing fractions with the same denominator, we can just compare the numerators.",
        "For example, if we compare 3/5 and 4/5 we are comparing 3 lots of 1/5 and 4 lots of 1/5. Since 3 is less than 4, 3/7 < 4/7."
      ],
      "challengeSeed": [
        "% Replace the ? below with \\lt (less than), \\gt (greater than) or = (equal).",
        "\\[",
        "\\frac{7}{9} ? \\frac{4}{9}",
        "\\]"
      ],
      "tests": [
        "assert(/\\\\frac\\{7\\}\\{9\\}/g.test(expression), 'message: Compare the fraction 7/9')",
        "assert(/\\\\frac\\{4\\}\\{9\\}/g.test(expression), 'message: Compare the fraction 4/9')",
        "assert(/\\\\frac\\{7\\}\\{9\\}\\s*\\\\gt\\s*\\\\frac\\{4\\}\\{9\\}/g.test(expression), 'message: Add the correct comparison operator between the fractions.')"
      ],
      "solutions": [
        "%  \\[ \\frac{7}{9} \\gt \\frac{4}{9} \\]"
      ]
    }
  ]
}
